aioshutdown/__init__.py
aioshutdown/_common.py
aioshutdown/_shutdown.py
aioshutdown/_types.py
aioshutdown/py.typed
aioshutdown-0.0.4.dist-info/LICENSE
aioshutdown-0.0.4.dist-info/METADATA
aioshutdown-0.0.4.dist-info/WHEEL
aioshutdown-0.0.4.dist-info/top_level.txt
aioshutdown-0.0.4.dist-info/RECORD
