Metadata-Version: 2.1
Name: aioshutdown
Version: 0.0.4
Summary: Context manager that provides simple graceful shutdown interface for your asyncio tasks.
Author-email: Ali Aliyev <ali@aliev.me>
Project-URL: Homepage, https://github.com/aliev/aioshutdown
Project-URL: Bug Tracker, https://github.com/aliev/aioshutdown/issues
Keywords: asyncio,graceful,shutdown
Classifier: Development Status :: 5 - Production/Stable
Classifier: Intended Audience :: Developers
Classifier: Programming Language :: Python
Classifier: License :: OSI Approved :: MIT License
Classifier: Natural Language :: English
Classifier: Operating System :: OS Independent
Classifier: Programming Language :: Python
Classifier: Programming Language :: Python :: 3
Classifier: Programming Language :: Python :: 3.8
Classifier: Programming Language :: Python :: 3.9
Classifier: Programming Language :: Python :: 3.10
Classifier: Framework :: AsyncIO
Classifier: Topic :: Software Development :: Libraries :: Python Modules
Classifier: Topic :: Utilities
Requires-Python: >=3.8
License-File: LICENSE
Requires-Dist: typing-extensions
Provides-Extra: dev
Requires-Dist: pre-commit ; extra == 'dev'
Requires-Dist: wheel ; extra == 'dev'
Requires-Dist: twine ; extra == 'dev'
Requires-Dist: build ; extra == 'dev'
Requires-Dist: pytest ; extra == 'dev'
Requires-Dist: pytest-cov ; extra == 'dev'
Requires-Dist: mypy ; extra == 'dev'
Requires-Dist: flake8 ; extra == 'dev'
Requires-Dist: flake8-pyproject ; extra == 'dev'
